tokko_mq_utils/__init__.py
tokko_mq_utils/core.py
tokko_mq_utils/errors.py
tokko_mq_utils-0.0.2.dist-info/METADATA
tokko_mq_utils-0.0.2.dist-info/WHEEL
tokko_mq_utils-0.0.2.dist-info/top_level.txt
tokko_mq_utils-0.0.2.dist-info/RECORD
